helloingestion/__init__.py
helloingestion/wp.py
helloingestion-1.0.dist-info/METADATA
helloingestion-1.0.dist-info/WHEEL
helloingestion-1.0.dist-info/top_level.txt
helloingestion-1.0.dist-info/RECORD
