Metadata-Version: 2.1
Name: helloingestion
Version: 1.0
Summary: 一个非常NM的包
Author: zxh
Author-email: zxh@qq.com
Classifier: Programming Language :: Python :: 3
Classifier: License :: OSI Approved :: MIT License
Classifier: Operating System :: OS Independent
Requires-Dist: pillow
